StockHero/StockExchange.py
StockHero/Ticker.py
StockHero/__init__.py
StockHero/__version__.py
StockHero/Ticker_Sources/BoersengefluesterRequest.py
StockHero/Ticker_Sources/GuruFocusRequest.py
StockHero/Ticker_Sources/MorningStarRequest.py
StockHero/Ticker_Sources/NASDAQRequest.py
StockHero/Ticker_Sources/StratosphereRequest.py
StockHero/Ticker_Sources/TickerRequest.py
StockHero/Ticker_Sources/TraderFoxRequest.py
StockHero/Ticker_Sources/YahooRequest.py
StockHero/Ticker_Sources/__init__.py
stockhero-0.4.21.dist-info/METADATA
stockhero-0.4.21.dist-info/WHEEL
stockhero-0.4.21.dist-info/licenses/LICENSE
stockhero-0.4.21.dist-info/RECORD
