Metadata-Version: 2.4
Name: StockHero
Version: 0.4.21
Summary: market data from finance APIs and other publicy available sources
Author: RobWen
Author-email: RobWen.StockHero@gmail.com
License-File: LICENSE
Classifier: License :: OSI Approved :: Apache Software License
Classifier: Operating System :: OS Independent
Classifier: Programming Language :: Python :: 3
Classifier: Topic :: Office/Business :: Financial :: Investment
Requires-Python: >=3.6
Requires-Dist: beautifulsoup4>=4.12.2
Requires-Dist: pandas>=2.0.3
Requires-Dist: requests>=2.31.0
